apitoolkit_django/__init__.py
apitoolkit_django-2.0.1.dist-info/METADATA
apitoolkit_django-2.0.1.dist-info/WHEEL
apitoolkit_django-2.0.1.dist-info/top_level.txt
apitoolkit_django-2.0.1.dist-info/RECORD
