Metadata-Version: 2.1
Name: apitoolkit-django
Version: 2.0.1
Summary: A Django SDK for Apitoolkit integration
Author: APIToolkit
Author-email: hello@apitoolkit.io
Requires-Dist: Django
Requires-Dist: apitoolkit-common
Requires-Dist: opentelemetry-api>=1.0.0
